{
  "_fv": 28,
  "_type": "tool",
  "definition": {
    "renderType": 0,
    "texture": "tungsten_hoe",
    "customModelName": "Normal",
    "name": "Tungsten Hoe",
    "specialInfo": [],
    "creativeTab": {
      "value": "TOOLS"
    },
    "toolType": "Hoe",
    "harvestLevel": 3,
    "efficiency": 7.0,
    "attackSpeed": 3.5,
    "enchantability": 12,
    "damageVsEntity": 1.0,
    "usageCount": 1000,
    "blocksAffected": [],
    "hasGlow": false,
    "repairItems": [
      {
        "value": ""
      },
      {
        "value": "CUSTOM:TungstenIngot"
      }
    ],
    "immuneToFire": true,
    "stayInGridWhenCrafting": false,
    "damageOnCrafting": false
  }
}